yta_video_masking/__init__.py
yta_video_masking/alphascreen/__init__.py
yta_video_masking/greenscreen/__init__.py
yta_video_masking/greenscreen/threed.py
yta_video_masking/greenscreen/utils.py
yta_video_masking/region_filler.py
yta_video_masking-0.0.2.dist-info/licenses/LICENSE
yta_video_masking-0.0.2.dist-info/METADATA
yta_video_masking-0.0.2.dist-info/WHEEL
yta_video_masking-0.0.2.dist-info/RECORD
