Metadata-Version: 2.4
Name: yta-video-masking
Version: 0.0.2
Summary: Youtube Autonomous Video Masking Module
License-File: LICENSE
Author: danialcala94
Author-email: danielalcalavalera@gmail.com
Requires-Python: ==3.9
Classifier: Programming Language :: Python :: 3
Classifier: Programming Language :: Python :: 3.9
Requires-Dist: moviepy (>=0.0.1,<9.0.0)
Requires-Dist: yta_constants (>=0.0.1,<1.0.0)
Requires-Dist: yta_image_base (>=0.0.1,<1.0.0)
Requires-Dist: yta_image_masking (>=0.0.1,<1.0.0)
Requires-Dist: yta_positioning (>=0.0.1,<1.0.0)
Requires-Dist: yta_validation (>=0.0.1,<1.0.0)
Requires-Dist: yta_video_utils (>=0.0.1,<1.0.0)
